radinNFP/__init__.py
Radinfp-0.0.1.dist-info/METADATA
Radinfp-0.0.1.dist-info/WHEEL
Radinfp-0.0.1.dist-info/top_level.txt
Radinfp-0.0.1.dist-info/RECORD
